Metadata-Version: 2.1
Name: minolz
Version: 1.1
Summary: A python library that can download any files in a few lines
Home-page: http://liztochekcodesoon.epizy.com/
Author: liztochekcode <liztochekcode@gmail.com>
License: Public Domain
Classifier: Environment :: Console
Classifier: License :: Public Domain
Classifier: Operating System :: OS Independent
Classifier: Programming Language :: Python :: 2
Classifier: Programming Language :: Python :: 3
Classifier: Topic :: Software Development :: Libraries :: Python Modules
Classifier: Topic :: System :: Networking
Classifier: Topic :: Utilities
